{
  "default_state": "Level1.FlyPerson",
  "states": {
    "Level1.FlyPerson": {
      "runs": [
        {
          "name": "ppo-10M",
          "agent": "ppo",
          "hyperparameters": {
            "timesteps": 10000000,
            "time_limit": 4500
          },
          "rewards": {
            "mean": 2365.056206649127,
            "first_10_mean": 705.0,
            "final_10_mean": 3670.0,
            "median": 2750.0,
            "max": 4750.0
          }
        }
      ]
    }
  }
}
