{
  "done": {
    "condition": "all",
    "variables": {
      "health": {
        "op": "zero"
      },
      "lives": {
        "op": "zero"
      }
    }
  },
  "reward": {
    "variables": {
      "score0": {
        "penalty": 1.0,
        "reward": 1.0
      },
      "score1": {
        "penalty": 10.0,
        "reward": 10.0
      },
      "score2": {
        "penalty": 100.0,
        "reward": 100.0
      },
      "score3": {
        "penalty": 1000.0,
        "reward": 1000.0
      },
      "score4": {
        "penalty": 10000.0,
        "reward": 10000.0
      },
      "score5": {
        "penalty": 100000.0,
        "reward": 100000.0
      }
    }
  }
}
